{
  "IsRegenerate": true,
  "MenuPosition": "main",
  "RelativeNamespace": "Surpath",
  "EntityName": "ConfirmationValue",
  "EntityNamePlural": "ConfirmationValues",
  "TableName": "ConfirmationValues",
  "PrimaryKeyType": "Guid",
  "BaseClass": "Entity",
  "EntityHistory": true,
  "AutoMigration": false,
  "UpdateDatabase": false,
  "CreateUserInterface": true,
  "CreateViewOnly": true,
  "CreateExcelExport": true,
  "IsNonModalCRUDPage": true,
  "IsMasterDetailPage": false,
  "PagePermission": {
    "Host": true,
    "Tenant": false
  },
  "Properties": [
    {
      "Name": "ScreenValue",
      "Type": "double",
      "MaxLength": -1,
      "MinLength": -1,
      "Range": {
        "IsRangeSet": false,
        "MinimumValue": 0.0,
        "MaximumValue": 0.0
      },
      "Required": false,
      "Nullable": false,
      "Regex": "",
      "UserInterface": {
        "AdvancedFilter": true,
        "List": true,
        "CreateOrUpdate": true
      },
      "ViewType": null
    },
    {
      "Name": "ConfirmValue",
      "Type": "double",
      "MaxLength": -1,
      "MinLength": -1,
      "Range": {
        "IsRangeSet": false,
        "MinimumValue": 0.0,
        "MaximumValue": 0.0
      },
      "Required": false,
      "Nullable": false,
      "Regex": "",
      "UserInterface": {
        "AdvancedFilter": true,
        "List": true,
        "CreateOrUpdate": true
      },
      "ViewType": null
    },
    {
      "Name": "UnitOfMeasurement",
      "Type": "EnumUnitOfMeasurement",
      "MaxLength": -1,
      "MinLength": -1,
      "Range": {
        "IsRangeSet": false,
        "MinimumValue": 0.0,
        "MaximumValue": 0.0
      },
      "Required": false,
      "Nullable": false,
      "Regex": "",
      "UserInterface": {
        "AdvancedFilter": true,
        "List": true,
        "CreateOrUpdate": true
      },
      "ViewType": null
    }
  ],
  "NavigationProperties": [
    {
      "Namespace": "inzibackend.Surpath",
      "ForeignEntityName": "Drug",
      "IdType": "Guid",
      "IsNullable": false,
      "PropertyName": "DrugId",
      "DisplayPropertyName": "Name",
      "DuplicationNumber": 0,
      "RelationType": "single",
      "ViewType": "LookupTable"
    },
    {
      "Namespace": "inzibackend.Surpath",
      "ForeignEntityName": "TestCategory",
      "IdType": "Guid",
      "IsNullable": false,
      "PropertyName": "TestCategoryId",
      "DisplayPropertyName": "Name",
      "DuplicationNumber": 0,
      "RelationType": "single",
      "ViewType": "Dropdown"
    }
  ],
  "NavigationPropertyOneToManyTables": [],
  "EnumDefinitions": [
    {
      "Name": "EnumUnitOfMeasurement",
      "Namespace": "inzibackend.Surpath",
      "EnumProperties": [
        {
          "Name": "ngml",
          "Value": 0
        },
        {
          "Name": "pgmg",
          "Value": 1
        }
      ]
    }
  ],
  "DbContext": null
}